parvusdb/__init__.py
parvusdb/utils/__init__.py
parvusdb/utils/aux.py
parvusdb/utils/cache.py
parvusdb/utils/code_container.py
parvusdb/utils/graph_builder.py
parvusdb/utils/graph_database.py
parvusdb/utils/match.py
parvusdb/utils/node_matcher.py
parvusdb-0.0.27.dist-info/METADATA
parvusdb-0.0.27.dist-info/WHEEL
parvusdb-0.0.27.dist-info/top_level.txt
parvusdb-0.0.27.dist-info/RECORD
